[{"model": "workforce.thirdpartypayer", "fields": {"name": "assurance_maladie", "label": "public health insurance", "label_en": "public health insurance", "label_fr": "sécurité sociale", "definition": null, "definition_en": null, "definition_fr": null}}, {"model": "workforce.thirdpartypayer", "fields": {"name": "complementary_health_insurance", "label": "complementary health insurance", "label_en": "complementary health insurance", "label_fr": "mutuelle", "definition": null, "definition_en": null, "definition_fr": null}}]